LICENSE
MANIFEST.in
README.md
requirements.txt
setup.py
r6sapi/__init__.py
r6sapi/auth.py
r6sapi/exceptions.py
r6sapi/gamemodes.py
r6sapi/gamequeues.py
r6sapi/operators.py
r6sapi/platforms.py
r6sapi/players.py
r6sapi/ranks.py
r6sapi/weapons.py
r6sapi.egg-info/PKG-INFO
r6sapi.egg-info/SOURCES.txt
r6sapi.egg-info/dependency_links.txt
r6sapi.egg-info/requires.txt
r6sapi.egg-info/top_level.txt