Metadata-Version: 2.1
Name: r6sapi
Version: 1.2.0
Summary: Interface for Ubisoft API
Home-page: https://github.com/billy-yoyo/RainbowSixSiege-Python-API
Author: billyoyo
Author-email: billyoyo@hotmail.co.uk
License: MIT
Platform: UNKNOWN
Classifier: Development Status :: 4 - Beta
Classifier: License :: OSI Approved :: MIT License
Classifier: Intended Audience :: Developers
Classifier: Natural Language :: English
Classifier: Operating System :: OS Independent
Classifier: Programming Language :: Python :: 3.4
Classifier: Programming Language :: Python :: 3.5
Classifier: Topic :: Internet
Classifier: Topic :: Software Development :: Libraries
Classifier: Topic :: Software Development :: Libraries :: Python Modules
Classifier: Topic :: Utilities
